Mux2.v
module mux2(data1,data2,sel,out);
    input [31:0] data1,data2;
    input sel;
    output reg [31:0] out;
    always @ (*)begin
        case(sel)
            0 : out = data1;
            1 : out = data2;
        endcase
    end
endmodule


module mux3(data1,data2,sel,out);
    input [31:0] data1,data2;
    input sel;
    output reg [31:0] out;
    always @ (*) begin
        case(sel)
            0 : out = data1;
            1 : out = data2;
        endcase
    end
endmodule

Main_memory.v
module MainMemory(memread,memwrite,address,data_in,data_out,d11,d12,d13,d21,d22,d23,d31,d32,d33);
input memread;
input memwrite;
input [31:0]address;
input [31:0]data_in;

output reg [31:0]data_out;
output reg [31:0] d11, d12, d13, d21, d22, d23, d31, d32, d33;

reg [31:0] matrix1[8:0];
reg [31:0] matrix2[8:0];
reg [31:0] matrix3[8:0];

initial begin
	matrix3[0]=0;
	matrix3[1]=0;
	matrix3[2]=0;
	matrix3[3]=0;
	matrix3[4]=0;
	matrix3[5]=0;
	matrix3[6]=0;
	matrix3[7]=0;
	matrix3[8]=0;
end

always@(*)
	begin
		matrix1[0]=1024;
		matrix1[1]=1024;
		matrix1[2]=1024;
		matrix1[3]=1024;
		matrix1[4]=1024;
		matrix1[5]=1024;
		matrix1[6]=1024;
		matrix1[7]=1024;
		matrix1[8]=1024;

		matrix2[0]=256;
		matrix2[1]=256;
		matrix2[2]=256;
		matrix2[3]=256;
		matrix2[4]=256;
		matrix2[5]=256;
		matrix2[6]=256;
		matrix2[7]=256;
		matrix2[8]=256;

		if(memread==1 && memwrite==0)
		begin

			case(address)
				32'b0000001000000000 : data_out=matrix1[0];
				32'b0000001000000100 : data_out=matrix1[1];
				32'b0000001000001000 : data_out=matrix1[2];
				32'b0000001000001100 : data_out=matrix1[3];
				32'b0000001000010000 : data_out=matrix1[4];
				32'b0000001000010100 : data_out=matrix1[5];
				32'b0000001000011000 : data_out=matrix1[6];
				32'b0000001000011100 : data_out=matrix1[7];
				32'b0000001000100000 : data_out=matrix1[8];

				32'b0000001100000000 : data_out=matrix2[0];
				32'b0000001100000100 : data_out=matrix2[1];
				32'b0000001100001000 : data_out=matrix2[2];
				32'b0000001100001100 : data_out=matrix2[3];
				32'b0000001100010000 : data_out=matrix2[4];
				32'b0000001100010100 : data_out=matrix2[5];
				32'b0000001100011000 : data_out=matrix2[6];
				32'b0000001100011100 : data_out=matrix2[7];
				32'b0000001100100000 : data_out=matrix2[8];
				default : data_out=32'd0;
			endcase

		end

		else if(memwrite==1 && memread==0)
			begin
				case(address)
					32'b0000000100000000 : matrix3[0]=data_in;
					32'b0000000100000100 : matrix3[1]=data_in;
					32'b0000000100001000 : matrix3[2]=data_in;
					32'b0000000100001100 : matrix3[3]=data_in;
					32'b0000000100010000 : matrix3[4]=data_in;
					32'b0000000100010100 : matrix3[5]=data_in;
					32'b0000000100011000 : matrix3[6]=data_in;
					32'b0000000100011100 : matrix3[7]=data_in;
					32'b0000000100100000 : matrix3[8]=data_in;
					default : data_out=data_in;
				endcase
			end

	d11 = matrix3[0];
	d12 = matrix3[1];
	d13 = matrix3[2];
	d21 = matrix3[3];
	d22 = matrix3[4];
	d23 = matrix3[5];
	d31 = matrix3[6];
	d32 = matrix3[7];
	d33 = matrix3[8];
end

	/*
	initial begin
	$display("%d",data_in);
	//$display("%d %d %d %d %d %d",d11,d12,d13,d21,d22,d23);
	end
	*/

endmodule

ALU_Main.v
module aluMain(controlLines, a, b, out);
    input [3:0] controlLines;
    input [31:0] a, b;
    output reg [31:0] out;
    always @ (*) begin
        case(controlLines)
            4'b0010 : out = a + b;
            4'b0011 : out = a - b;
            4'b0100 : out = a * b;
        endcase
    end
endmodule

ALU_Control_Unit.v
module aluControlUnit(aluOp, f6, out4);
    input [1:0] aluOp;
    input [5:0] f6;
    output reg [3:0] out4;
    always @ (*)
        begin
            case(aluOp)
                2'b00 : out4=4'b0010;
                2'b10 : case(f6)
                            6'b100000 : out4 = 4'b0010;
                            6'b100010 : out4 = 4'b0011;
                            6'b011000 : out4 = 4'b0100;
                        endcase
            endcase
        end
endmodule

Register.v
module Registers(pc,regWrite,write_back,address1,address2,address3,dataOut1,dataOut2);
    input regWrite;
    input [31:0] pc;
    input [4:0] address1,address2,address3;
    input [31:0] write_back;

    output reg [31:0] dataOut1;
    output reg [31:0] dataOut2;

    reg [31:0] registers[23:0];
    reg [31:0] count;

    initial begin
        registers[8]=32'b0;
        registers[9]=32'b0;
        registers[10]=32'b0;
        registers[11]=32'b0;
        registers[12]=32'b0;
        registers[13]=32'b0;
        registers[14]=32'b0;
        registers[15]=32'b0;
        registers[16]=32'b0;
        registers[17]=32'b0;
        registers[18]=32'b0;
        registers[19]=32'b0;
        registers[20]=32'b0;
        registers[21]=32'b0;
        registers[22]=32'b0;
        registers[23]=32'b0;
        count=0;
    end

    always @ (*)
        begin

            if(regWrite==1 && count!=pc)
                begin
                    case(address1)
                              5'b01000 : registers[9]=write_back;
                              5'b10001 : registers[10]=write_back;
                              5'b01001 : registers[11]=write_back;
                              5'b10010 : registers[12]=write_back;
                              5'b01010 : registers[13]=write_back;
                              5'b10011 : registers[14]=write_back;
                              5'b01011 : registers[15]=write_back;
                              5'b10100 : registers[16]=write_back;
                              5'b01100 : registers[17]=write_back;
                              5'b10101 : registers[18]=write_back;
                              5'b01101 : registers[19]=write_back;
                              5'b10110 : registers[20]=write_back;
                              5'b01110 : registers[21]=write_back;
                              5'b10111 : registers[22]=write_back;
                              5'b01111 : registers[23]=write_back;
                              default : registers[8]=32'b0;
                    endcase
                count = pc;
                end

                case(address2)
                    5'b10000 : dataOut1=registers[8];
                    5'b01000 :  dataOut1=registers[9];
                    5'b10001 : dataOut1=registers[10];
                    5'b01001 : dataOut1=registers[11];
                    5'b10010 : dataOut1=registers[12];
                    5'b01010 : dataOut1=registers[13];
                    5'b10011 : dataOut1=registers[14];
                    5'b01011 : dataOut1=registers[15];
                    5'b10100 : dataOut1=registers[16];
                    5'b01100 : dataOut1=registers[17];
                    5'b10101 : dataOut1=registers[18];
                    5'b01101 : dataOut1=registers[19];
                    5'b10110 : dataOut1=registers[20];
                    5'b01110 : dataOut1=registers[21];
                    5'b10111 : dataOut1=registers[22];
                    5'b01111 : dataOut1=registers[23];
                    default : dataOut1=32'b0;
                endcase

            case(address3)
                5'b10000 : dataOut2=registers[8];
                5'b01000 : dataOut2=registers[9];
                5'b10001 : dataOut2=registers[10];
                5'b01001 : dataOut2=registers[11];
                5'b10010 : dataOut2=registers[12];
                5'b01010 : dataOut2=registers[13];
                5'b10011 : dataOut2=registers[14];
                5'b01011 : dataOut2=registers[15];
                5'b10100 : dataOut2=registers[16];
                5'b01100 : dataOut2=registers[17];
                5'b10101 : dataOut2=registers[18];
                5'b01101 : dataOut2=registers[19];
                5'b10110 : dataOut2=registers[20];
                5'b01110 : dataOut2=registers[21];
                5'b10111 : dataOut2=registers[22];
                5'b01111 : dataOut2=registers[23];
                default : dataOut2=32'b0;
            endcase

            /*
                $display("out1,out2,addr2,addr3= %d %d %d %d",dataOut1,dataOut2,address2,address3);
                $display("\nregisters:\n s0=%b t0=%b\n s1=%b t1=%b\n s2=%b t2=%b\n s3=%b t3=%b\n s4=%b t4=%b\n s5=%b t5=%b\n s6=%b t6=%b\n s7=%b t7=%b\n",registers[8],registers[9],registers[10],registers[11],registers[12],
                registers[13],registers[14],registers[15],registers[16],registers[17],registers[18],registers[19],registers[20],registers[21],registers[22],
                registers[23]);
            */
        end
endmodule

Decoder.v
module decoder(pc,regwrite,write_back,dest,address1,address2,out1,out2);
    input  regwrite;
    input [31:0] pc;
    input [31:0]write_back;
    input [4:0] address1,address2,dest;
    output [31:0] out1,out2;

Registers uut1(pc,regwrite,write_back,dest,address1,address2,out1,out2);
    /*
    always@(*)
        begin
            $display("\nwrite_back = %b\n",write_back);
        end
    */
endmodule

Mux1.v
module mux1(data1,data2,sel,out);
    input [4:0] data1,data2;
    input sel;
    output reg [4:0] out;

    always @ (*)begin//posedge  begin
        case(sel)
            0 : out = data1;
            1 : out = data2;
        endcase
        // $display("mux1\nd1, d2 = %b, %b\nout = %b", data1, data2, out);
    end
endmodule

Control_Unit.v
module controlUnit(instruction, opcode, ALUout, MemR, MemW, RegW, MemToReg, aluSrc, regDest);
    input [5:0] opcode;
    input [31:0] instruction;
    output reg [1:0] ALUout;
    output reg MemR, MemW, RegW, MemToReg, aluSrc, regDest;

    always @ (*)
        begin
            case(opcode)
                6'b000000 : begin
                                ALUout = 2'b10;
                                RegW = 1;
                                MemR = 0;
                                MemW = 0;
                                MemToReg = 0;
                                aluSrc = 0;
                                regDest = 1;
                            end
                6'b100011 : begin
                                ALUout = 2'b00;
                                RegW = 1;
                                MemR = 1;
                                MemToReg = 1;
                                MemW = 0;
                                aluSrc = 1;
                                regDest = 0;
                            end
                6'b101011 : begin
                                ALUout = 2'b00;
                                RegW = 0;
                                MemR = 0;
                                MemToReg = 1;
                                MemW = 1;
                                aluSrc = 1;
                                regDest = 0;
                            end
            endcase
        end
endmodule

Instruction_memory.v
module instruction_memory(address,data_out);
input [31:0]address;
output  [31:0] data_out;
reg [31:0]memory[360:0];
initial begin

		//load word t0 512(s0)
		memory[0]=32'b100011_10000_01000_0000001000000000;
		//load word t1 768(s0)
		memory[4]=32'b100011_10000_01001_0000001100000000;
		//load word t2 516(s0)
		memory[8]=32'b100011_10000_01010_0000001000000100;
		//load word t3 772(s0)
		memory[12]=32'b100011_10000_01011_0000001100000100;
		//load word t4 520(s0)
		memory[16]=32'b100011_10000_01100_0000001000001000;
		//load word t5 776(s0)
		memory[20]=32'b100011_10000_01101_0000001100001000;
		//mul t0 t1 t6
		memory[24]=32'b000000_01000_01001_01110_00000_011000;
		//mul t2 t3 t7
		memory[28]=32'b000000_01010_01011_01111_00000_011000;
		//mul t4 t5 s5
		memory[32]=32'b000000_01100_01101_10101_00000_011000;
		//add t6 t7 t6
		memory[36]=32'b000000_01110_01111_01110_00000_100000;
		//add t6 s5 t6
		memory[40]=32'b000000_01110_10101_01110_00000_100000;
		//
		//store word t6 256(s0)
		memory[44]=33'b101011_10000_01110_0000000100000000;
		//
		//load word t1 780(s0)
		memory[48]=32'b100011_10000_01001_0000001100001100;
		//load word t3 784(s0)
		memory[52]=32'b100011_10000_01011_0000001100010000;
		//load word t5 788(s0)
		memory[56]=32'b100011_10000_01101_0000001100010100;
		//mul t0 t1 t6
		memory[60]=32'b000000_01000_01001_01110_00000_011000;
		//mul t2 t3 t7
		memory[64]=32'b000000_01010_01011_01111_00000_011000;
		//mul t4 t5 s5
		memory[68]=32'b000000_01100_01101_10101_00000_011000;
		//add t6 t7 t6
		memory[72]=32'b000000_01110_01111_01110_00000_100000;
		//add t6 s5 t6
		memory[76]=32'b000000_01110_10101_01110_00000_100000;
		//
		//store word t6 260(s0)
		memory[80]=32'b101011_10000_01110_0000000100000100;
		//
		//load word t1 792(s0)
		memory[84]=32'b100011_10000_01001_0000001100011000;
		//load word t3 796(s0)
		memory[88]=32'b100011_10000_01011_0000001100011100;
		//load word t5 800(s0)
		memory[92]=32'b100011_10000_01101_0000001100100000;
		//mul t0 t1 t6
		memory[96] =32'b000000_01000_01001_01110_00000_011000;
		//mul t2 t3 t7
		memory[100]=32'b000000_01010_01011_01111_00000_011000;
		//mul t4 t5 s5
		memory[104]=32'b000000_01100_01101_10101_00000_011000;
		//add t6 t7 t6
		memory[108]=32'b000000_01110_01111_01110_00000_100000;
		//add t6 s5 t6
		memory[112]=32'b000000_01110_10101_01110_00000_100000;
		//
		//store word t6 264(s0)
		memory[116]=32'b101011_10000_01110_0000000100001000;
		//
		//load word t0 524(s0)
		memory[120]=32'b100011_10000_01000_0000001000001100;
		//load word t2 528(s0)
		memory[124]=32'b100011_10000_01010_0000001000010000;
		//load word t4 532(s0)
		memory[128]=32'b100011_10000_01100_0000001000010100;
		//load word t1 768(s0)
		memory[132]=32'b100011_10000_01001_0000001100000000;
		//load word t3 772(s0)
		memory[136]=32'b100011_10000_01011_0000001100000100;
		//load word t5 776(s0)
		memory[140]=32'b100011_10000_01101_0000001100001000;
		//mul t0 t1 t6
		memory[144]=32'b000000_01000_01001_01110_00000_011000;
		//mul t2 t3 t7
		memory[148]=32'b000000_01010_01011_01111_00000_011000;
		//mul t4 t5 s5
		memory[152]=32'b000000_01100_01101_10101_00000_011000;
		//add t6 t7 t6
		memory[156]=32'b000000_01110_01111_01110_00000_100000;
		//add t6 s5 t6
		memory[160]=32'b000000_01110_10101_01110_00000_100000;
		//
		//store word t6 268(s0)
		memory[164]=32'b101011_10000_01110_0000000100001100;
		//
		//load t1 780(s0)
		memory[168]=32'b100011_10000_01001_0000001100001100;
		//load t3 784(s0)
		memory[172]=32'b100011_10000_01011_0000001100010000;
		//load t5 788(s0)
		memory[176]=32'b100011_10000_01101_0000001100010100;
		//mul t0 t1 t6
		memory[180]=32'b000000_01000_01001_01110_00000_011000;
		//mul t2 t3 t7
		memory[184]=32'b000000_01010_01011_01111_00000_011000;
		//mul t4 t5 s5
		memory[188]=32'b000000_01100_01101_10101_00000_011000;
		//add t6 t7 t6
		memory[192]=32'b000000_01110_01111_01110_00000_100000;
		//add t6 s5 t6
		memory[196]=32'b000000_01110_10101_01110_00000_100000;
		//
		//store word t6 272(s0)
		memory[200]=32'b101011_10000_01110_0000000100010000;
		//
		//load t1 792(s0)
		memory[204]=32'b100011_10000_01001_0000001100011000;
		//load t3 796(s0)
		memory[208]=32'b100011_10000_01011_0000001100011100;
		//load t5 800(s0)
		memory[212]=32'b100011_10000_01101_0000001100100000;
		//mul t0 t1 t6
		memory[216]=32'b000000_01000_01001_01110_00000_011000;
		//mul t2 t3 t7
		memory[220]=32'b000000_01010_01011_01111_00000_011000;
		//mul t4 t5 s5
		memory[224]=32'b000000_01100_01101_10101_00000_011000;
		//add t6 t7 t6
		memory[228]=32'b000000_01110_01111_01110_00000_100000;
		//add t6 s5 t6
		memory[232]=32'b000000_01110_10101_01110_00000_100000;
		//
		//store word t6 276(s0)
		memory[236]=32'b101011_10000_01110_0000000100010100;
		//
		//load t0 536(s0)
		memory[240]=32'b100011_10000_01000_0000001000011000;
		//load t2 540(s0)
		memory[244]=32'b100011_10000_01010_0000001000011100;
		//load t4 544(s0)
		memory[248]=32'b100011_10000_01100_0000001000100000;
		//load t1 768(s0)
		memory[252]=32'b100011_10000_01001_0000001100000000;
		//load t3 772(s0)
		memory[256]=32'b100011_10000_01011_0000001100000100;
		//load t5 776(s0)
		memory[260]=32'b100011_10000_01101_0000001100001000;
		//mul t0 t1 t6
		memory[264]=32'b000000_01000_01001_01110_00000_011000;
		//mul t2 t3 t7
		memory[268]=32'b000000_01010_01011_01111_00000_011000;
		//mul t4 t5 s5
		memory[272]=32'b000000_01100_01101_10101_00000_011000;
		//add t6 t7 t6
		memory[276]=32'b000000_01110_01111_01110_00000_100000;
		//add t6 s5 t6
		memory[280]=32'b000000_01110_10101_01110_00000_100000;
		//
		//store word t6 280(s0)
		memory[284]=32'b101011_10000_01110_0000000100011000;
		//
		//load t1 780(s0)
		memory[288]=32'b100011_10000_01001_0000001100001100;
		//load t3 784(s0)
		memory[292]=32'b100011_10000_01011_0000001100010000;
		//load t5 788(s0)
		memory[296]=32'b100011_10000_01101_0000001100010100;
		//mul t0 t1 t6
		memory[300]=32'b000000_01000_01001_01110_00000_011000;
		//mul t2 t3 t7
		memory[304]=32'b000000_01010_01011_01111_00000_011000;
		//mul t4 t5 s5
		memory[308]=32'b000000_01100_01101_10101_00000_011000;
		//add t6 t7 t6
		memory[312]=32'b000000_01110_01111_01110_00000_100000;
		//add t6 s5 t6
		memory[316]=32'b000000_01110_10101_01110_00000_100000;
		//
		//store t6 284(s0)
		memory[320]=32'b101011_10000_01110_0000000100011100;
		//
		//load t1 792(s0)
		memory[324]=32'b100011_10000_01001_0000001100011000;
		//load t3 796(s0)
		memory[328]=32'b100011_10000_01011_0000001100011100;
		//load t5 800(s0)
		memory[332]=32'b100011_10000_01101_0000001100100000;
		//mul t0 t1 t6
		memory[336]=32'b000000_01000_01001_01110_00000_011000;
		//mul t2 t3 t7
		memory[340]=32'b000000_01010_01011_01111_00000_011000;
		//mul t4 t5 s5
		memory[344]=32'b000000_01100_01101_10101_00000_011000;
		//add t6 t7 t6
		memory[348]=32'b000000_01110_01111_01110_00000_100000;
		//add t6 s5 t6
		memory[352]=32'b000000_01110_10101_01110_00000_100000;
		//
		//store t6 288(s0)
		memory[356]=32'b101011_10000_01110_0000000100100000;
		//
end

assign data_out=memory[address];

/*
always @ ( * ) begin
	data_out = memory[address];
	$display("%b", data_out);
end
*/

endmodule

main.v
module main(pc,d11,d12,d13,d21,d22,d23,d31,d32,d33);
    input [31:0] pc;

    output [31:0] d11,d12,d13,d21,d22,d23,d31,d32,d33;
    // reg clk;
    wire [31:0] out1,out2,instruction,b,out_alu;
    wire MemR,MemW,RegW,MemToReg,alusrc,regdest;
    wire [1:0] Aluout;
    wire [4:0] dest;
    wire [3:0] c_lines;
    wire [31:0] signExtended,data_out_mem,write_back;

    assign signExtended = {16'b0, instruction[15:0]};

    genvar i;
    generate for(i=0;i<1;i=i+1)
        begin
            instruction_memory uut1(pc,instruction);
            controlUnit uut2(instruction,instruction[31:26],Aluout,MemR,MemW,RegW,MemToReg,alusrc,regdest);
            mux1 uut3(instruction[20:16],instruction[15:11],regdest,dest);
            decoder uut4(pc,RegW,write_back,dest,instruction[25:21],instruction[20:16],out1,out2);
            mux2 uut5(out2,signExtended,alusrc,b);
            aluControlUnit uut6(Aluout,instruction[5:0],c_lines);
            aluMain uut7(c_lines,out1,b,out_alu);
            MainMemory uut8(MemR,MemW,out_alu,out2,data_out_mem,d11,d12,d13,d21,d22,d23,d31,d32,d33);
            mux3 uut9(out_alu,data_out_mem,MemToReg,write_back);
        end
    endgenerate

    /*
    always @ ( * ) begin
      $display("pc = %d , instruction = %b , Aluop=%b , Aluout = %b , MemR = %b , MemW = %b , RegW = %b,\nMemToReg = %b , alusrc = %b, regdest = %b ,\ndest = %b , address1 = %b , address2 = %b , out1 = %b ,\nout2 = %b ,signExtended = %b , b = %b ,c_line = %b,\nout_alu = %b, data_out_mem = %b, write_back = %b\n",pc,instruction,instruction[31:26],Aluout,MemR,
              MemW,RegW,MemToReg,alusrc,regdest,dest,instruction[25:21],instruction[20:16],
              out1,oumatrix1t2,signExtended,b,c_line,out_alu,data_out_mem,write_back);
    end
    */

endmodule

Test_Bench.v
module TB_3x3_Multiplication;
    reg [31:0] pc;
    reg clk;

    wire [31:0] d11, d12, d13, d21, d22, d23, d31, d32, d33;

    main uut(
        .pc(pc),
        .d11(d11),
        .d12(d12),
        .d13(d13),
        .d21(d21),
        .d22(d22),
        .d23(d23),
        .d31(d31),
        .d32(d32),
        .d33(d33)
    );

    initial begin
        /*
        $dumpfile("mip3x3m.vcd");
        $dumpvars(0, TB_3x3_Multiplication);
        */
        clk = 0; pc = -4; #10;
        repeat(182) #10 clk = ~clk;
    end

    always @ ( posedge clk ) begin
        if(pc!=356) pc = pc + 4;
        $display("%d \t%d \t%d\n%d \t%d \t%d\n%d \t%d \t%d\n", d11, d12, d13, d21, d22, d23, d31, d32, d33);
        // else pc = 356;
        //$display("pc = %d", pc);
        //$display("--------------------------------------------------------------\n");
    end
endmodule

graph.vcd
$date
	Mon Nov 26 11:48:11 2018
$end
$version
	Icarus Verilog
$end
$timescale
	1s
$end
$scope module TB_3x3_Multiplication $end
$var wire 32 ! d33 [31:0] $end
$var wire 32 " d32 [31:0] $end
$var wire 32 # d31 [31:0] $end
$var wire 32 $ d23 [31:0] $end
$var wire 32 % d22 [31:0] $end
$var wire 32 & d21 [31:0] $end
$var wire 32 ' d13 [31:0] $end
$var wire 32 ( d12 [31:0] $end
$var wire 32 ) d11 [31:0] $end
$var reg 1 * clk $end
$var reg 32 + pc [31:0] $end
$scope module uut $end
$var wire 32 , pc [31:0] $end
$var wire 32 - write_back [31:0] $end
$var wire 32 . signExtended [31:0] $end
$var wire 1 / regdest $end
$var wire 32 0 out_alu [31:0] $end
$var wire 32 1 out2 [31:0] $end
$var wire 32 2 out1 [31:0] $end
$var wire 32 3 instruction [31:0] $end
$var wire 5 4 dest [4:0] $end
$var wire 32 5 data_out_mem [31:0] $end
$var wire 32 6 d33 [31:0] $end
$var wire 32 7 d32 [31:0] $end
$var wire 32 8 d31 [31:0] $end
$var wire 32 9 d23 [31:0] $end
$var wire 32 : d22 [31:0] $end
$var wire 32 ; d21 [31:0] $end
$var wire 32 < d13 [31:0] $end
$var wire 32 = d12 [31:0] $end
$var wire 32 > d11 [31:0] $end
$var wire 4 ? c_lines [3:0] $end
$var wire 32 @ b [31:0] $end
$var wire 1 A alusrc $end
$var wire 1 B RegW $end
$var wire 1 C MemW $end
$var wire 1 D MemToReg $end
$var wire 1 E MemR $end
$var wire 2 F Aluout [1:0] $end
$scope begin genblk1[0] $end
$scope module uut1 $end
$var wire 32 G address [31:0] $end
$var wire 32 H data_out [31:0] $end
$upscope $end
$scope module uut2 $end
$var wire 32 I instruction [31:0] $end
$var wire 6 J opcode [5:0] $end
$var reg 2 K ALUout [1:0] $end
$var reg 1 E MemR $end
$var reg 1 D MemToReg $end
$var reg 1 C MemW $end
$var reg 1 B RegW $end
$var reg 1 A aluSrc $end
$var reg 1 / regDest $end
$upscope $end
$scope module uut3 $end
$var wire 5 L data1 [4:0] $end
$var wire 5 M data2 [4:0] $end
$var wire 1 / sel $end
$var reg 5 N out [4:0] $end
$upscope $end
$scope module uut4 $end
$var wire 5 O address1 [4:0] $end
$var wire 5 P address2 [4:0] $end
$var wire 5 Q dest [4:0] $end
$var wire 32 R pc [31:0] $end
$var wire 1 B regwrite $end
$var wire 32 S write_back [31:0] $end
$var wire 32 T out2 [31:0] $end
$var wire 32 U out1 [31:0] $end
$scope module uut1 $end
$var wire 5 V address1 [4:0] $end
$var wire 5 W address2 [4:0] $end
$var wire 5 X address3 [4:0] $end
$var wire 32 Y pc [31:0] $end
$var wire 1 B regWrite $end
$var wire 32 Z write_back [31:0] $end
$var reg 32 [ count [31:0] $end
$var reg 32 \ dataOut1 [31:0] $end
$var reg 32 ] dataOut2 [31:0] $end
$upscope $end
$upscope $end
$scope module uut5 $end
$var wire 32 ^ data1 [31:0] $end
$var wire 32 _ data2 [31:0] $end
$var wire 1 A sel $end
$var reg 32 ` out [31:0] $end
$upscope $end
$scope module uut6 $end
$var wire 2 a aluOp [1:0] $end
$var wire 6 b f6 [5:0] $end
$var reg 4 c out4 [3:0] $end
$upscope $end
$scope module uut7 $end
$var wire 32 d a [31:0] $end
$var wire 32 e b [31:0] $end
$var wire 4 f controlLines [3:0] $end
$var reg 32 g out [31:0] $end
$upscope $end
$scope module uut8 $end
$var wire 32 h address [31:0] $end
$var wire 32 i data_in [31:0] $end
$var wire 1 E memread $end
$var wire 1 C memwrite $end
$var reg 32 j d11 [31:0] $end
$var reg 32 k d12 [31:0] $end
$var reg 32 l d13 [31:0] $end
$var reg 32 m d21 [31:0] $end
$var reg 32 n d22 [31:0] $end
$var reg 32 o d23 [31:0] $end
$var reg 32 p d31 [31:0] $end
$var reg 32 q d32 [31:0] $end
$var reg 32 r d33 [31:0] $end
$var reg 32 s data_out [31:0] $end
$upscope $end
$scope module uut9 $end
$var wire 32 t data1 [31:0] $end
$var wire 32 u data2 [31:0] $end
$var wire 1 D sel $end
$var reg 32 v out [31:0] $end
$upscope $end
$upscope $end
$upscope $end
$upscope $end
$enddefinitions $end
#0
$dumpvars
b10000000000 v
b10000000000 u
b1000000000 t
b10000000000 s
b0 r
b0 q
b0 p
b0 o
b0 n
b0 m
b0 l
b0 k
b0 j
b0 i
b1000000000 h
b1000000000 g
b10 f
b1000000000 e
b0 d
b10 c
b0 b
b0 a
b1000000000 `
b1000000000 _
b0 ^
b0 ]
b0 \
b0 [
b10000000000 Z
b0 Y
b1000 X
b10000 W
b1000 V
b0 U
b0 T
b10000000000 S
b0 R
b1000 Q
b1000 P
b10000 O
b1000 N
b0 M
b1000 L
b0 K
b100011 J
b10001110000010000000001000000000 I
b10001110000010000000001000000000 H
b0 G
b0 F
1E
1D
0C
1B
1A
b1000000000 @
b10 ?
b0 >
b0 =
b0 <
b0 ;
b0 :
b0 9
b0 8
b0 7
b0 6
b10000000000 5
b1000 4
b10001110000010000000001000000000 3
b0 2
b0 1
b1000000000 0
0/
b1000000000 .
b10000000000 -
b0 ,
b0 +
0*
b0 )
b0 (
b0 '
b0 &
b0 %
b0 $
b0 #
b0 "
b0 !
$end
#20
b100000000 -
b100000000 S
b100000000 Z
b100000000 v
b100000000 5
b100000000 s
b100000000 u
b1100000000 0
b1100000000 g
b1100000000 h
b1100000000 t
b1001 4
b1001 N
b1001 Q
b1001 V
b1100000000 @
b1100000000 `
b1100000000 e
b1100000000 .
b1100000000 _
b1001 P
b1001 X
b1001 L
b0 1
b0 T
b0 ]
b0 ^
b0 i
b100 [
b10001110000010010000001100000000 3
b10001110000010010000001100000000 H
b10001110000010010000001100000000 I
b100 +
b100 ,
b100 G
b100 R
b100 Y
1*
#30
0*
#40
b10000000000 -
b10000000000 S
b10000000000 Z
b10000000000 v
b10000000000 5
b10000000000 s
b10000000000 u
b1000000100 0
b1000000100 g
b1000000100 h
b1000000100 t
b1010 4
b1010 N
b1010 Q
b1010 V
b1000000100 @
b1000000100 `
b1000000100 e
b1000000100 .
b1000000100 _
b100 b
b1010 P
b1010 X
b1010 L
b0 1
b0 T
b0 ]
b0 ^
b0 i
b1000 [
b10001110000010100000001000000100 3
b10001110000010100000001000000100 H
b10001110000010100000001000000100 I
b1000 +
b1000 ,
b1000 G
b1000 R
b1000 Y
1*
#50
0*
#60
b100000000 -
b100000000 S
b100000000 Z
b100000000 v
b100000000 5
b100000000 s
b100000000 u
b1100000100 0
b1100000100 g
b1100000100 h
b1100000100 t
b1011 4
b1011 N
b1011 Q
b1011 V
b1100000100 @
b1100000100 `
b1100000100 e
b1100000100 .
b1100000100 _
b1011 P
b1011 X
b1011 L
b0 1
b0 T
b0 ]
b0 ^
b0 i
b1100 [
b10001110000010110000001100000100 3
b10001110000010110000001100000100 H
b10001110000010110000001100000100 I
b1100 +
b1100 ,
b1100 G
b1100 R
b1100 Y
1*
#70
0*
#80
b10000000000 -
b10000000000 S
b10000000000 Z
b10000000000 v
b10000000000 5
b10000000000 s
b10000000000 u
b1000001000 0
b1000001000 g
b1000001000 h
b1000001000 t
b1100 4
b1100 N
b1100 Q
b1100 V
b1000001000 @
b1000001000 `
b1000001000 e
b1000001000 .
b1000001000 _
b1000 b
b1100 P
b1100 X
b1100 L
b0 1
b0 T
b0 ]
b0 ^
b0 i
b10000 [
b10001110000011000000001000001000 3
b10001110000011000000001000001000 H
b10001110000011000000001000001000 I
b10000 +
b10000 ,
b10000 G
b10000 R
b10000 Y
1*
#90
0*
#100
b100000000 -
b100000000 S
b100000000 Z
b100000000 v
b100000000 5
b100000000 s
b100000000 u
b1100001000 0
b1100001000 g
b1100001000 h
b1100001000 t
b1101 4
b1101 N
b1101 Q
b1101 V
b1100001000 @
b1100001000 `
b1100001000 e
b1100001000 .
b1100001000 _
b1101 P
b1101 X
b1101 L
b0 1
b0 T
b0 ]
b0 ^
b0 i
b10100 [
b10001110000011010000001100001000 3
b10001110000011010000001100001000 H
b10001110000011010000001100001000 I
b10100 +
b10100 ,
b10100 G
b10100 R
b10100 Y
1*
#110
0*
#120
b1000000000000000000 -
b1000000000000000000 S
b1000000000000000000 Z
b1000000000000000000 v
b1000000000000000000 0
b1000000000000000000 g
b1000000000000000000 h
b1000000000000000000 t
b100 ?
b100 c
b100 f
b10000000000 2
b10000000000 U
b10000000000 \
b10000000000 d
b1110 4
b1110 N
b1110 Q
b1110 V
1/
0A
0D
0E
b10 F
b10 K
b10 a
b100000000 @
b100000000 `
b100000000 e
b111000000011000 .
b111000000011000 _
b11000 b
b1001 P
b1001 X
b1000 O
b1000 W
b1110 M
b1001 L
b0 J
b100000000 1
b100000000 T
b100000000 ]
b100000000 ^
b100000000 i
b11000 [
b1000010010111000000011000 3
b1000010010111000000011000 H
b1000010010111000000011000 I
b11000 +
b11000 ,
b11000 G
b11000 R
b11000 Y
1*
#130
0*
#140
b1111 4
b1111 N
b1111 Q
b1111 V
b111100000011000 .
b111100000011000 _
b1011 P
b1011 X
b1010 O
b1010 W
b1111 M
b1011 L
b11100 [
b1010010110111100000011000 3
b1010010110111100000011000 H
b1010010110111100000011000 I
b11100 +
b11100 ,
b11100 G
b11100 R
b11100 Y
1*
#150
0*
#160
b10101 4
b10101 N
b10101 Q
b10101 V
b1010100000011000 .
b1010100000011000 _
b1101 P
b1101 X
b1100 O
b1100 W
b10101 M
b1101 L
b100000 [
b1100011011010100000011000 3
b1100011011010100000011000 H
b1100011011010100000011000 I
b100000 +
b100000 ,
b100000 G
b100000 R
b100000 Y
1*
#170
0*
#180
b10000000000000000000 -
b10000000000000000000 S
b10000000000000000000 Z
b10000000000000000000 v
b10000000000000000000 0
b10000000000000000000 g
b10000000000000000000 h
b10000000000000000000 t
b1000000000000000000 @
b1000000000000000000 `
b1000000000000000000 e
b10 ?
b10 c
b10 f
b1000000000000000000 1
b1000000000000000000 T
b1000000000000000000 ]
b1000000000000000000 ^
b1000000000000000000 i
b1000000000000000000 2
b1000000000000000000 U
b1000000000000000000 \
b1000000000000000000 d
b1110 4
b1110 N
b1110 Q
b1110 V
b111000000100000 .
b111000000100000 _
b100000 b
b1111 P
b1111 X
b1110 O
b1110 W
b1110 M
b1111 L
b100100 [
b1110011110111000000100000 3
b1110011110111000000100000 H
b1110011110111000000100000 I
b100100 +
b100100 ,
b100100 G
b100100 R
b100100 Y
1*
#190
0*
