Register.v
module Registers(regWrite, regAddress, dataIn, dataOut);
    input regWrite;
    input [4:0] regAddress;
    input [31:0] dataIn;

    output reg [31:0] dataOut;

    reg [31:0] R [15:0];

    initial begin
        case(regWrite)
            0 : dataOut = R[regAddress - 8];
            1 : begin
                    case(dataIn)
                        32'b? : R[regAddress - 8] = R[regAddress - 8];
                        default : R[regAddress - 8] = dataIn;
                    endcase
                end
        endcase
    end

endmodule //Registers

Mux2.v
module mux2(data1,data2,sel,out);
input [31:0] data1,data2;
input sel;
output reg [31:0] out;
always @ (*) begin
    case(sel)
        0 : out = data1;
        1 : out = data2;
    endcase
    $display("mux2\nd1, d2 = %d, %d\nout = %d", data1, data2, out);
end
endmodule

Main_memory.v
module MainMemory(memread,memwrite,address,data_in,data_out,d11,d12,d13,d21,d22,d23,d31,d32,d33);
input memread;
input memwrite;
input [31:0]address;
input [31:0]data_in;
output reg [31:0]data_out;
output [31:0] d11, d12, d13, d21, d22, d23, d31, d32, d33;
reg [31:0] matrix1[50:0];
reg [31:0] matrix2[50:0];
reg [31:0] matrix3[50:0];
initial begin
	matrix1[0]=32'd1;
	matrix1[1]=32'd2;
	matrix1[2]=32'd3;
	matrix1[3]=32'd4;
	matrix1[4]=32'd5;
	matrix1[5]=32'd6;
	matrix1[6]=32'd7;
	matrix1[7]=32'd8;
	matrix1[8]=32'd9;

	matrix2[0]=32'd1;
	matrix2[1]=32'd0;
	matrix2[2]=32'd0;
	matrix2[3]=32'd0;
	matrix2[4]=32'd1;
	matrix2[5]=32'd0;
	matrix2[6]=32'd0;
	matrix2[7]=32'd0;
	matrix2[8]=32'd1;

	/*matrix3[0]=32'd0;
	matrix3[1]=32'd0;
	matrix3[2]=32'd0;
	matrix3[3]=32'd0;
	matrix3[4]=32'd0;
	matrix3[5]=32'd0;
	matrix3[6]=32'd0;
	matrix3[7]=32'd0;
	matrix3[8]=32'd0;*/
	end
always@(*)
begin
	if(memread==1 && memwrite==0)
	begin
	case(address)
		32'b0000001000000000 : data_out=matrix1[0];
		32'b0000001000000100 : data_out=matrix1[1];
		32'b0000001000001000 : data_out=matrix1[2];
		32'b0000001000001100 : data_out=matrix1[3];
		32'b0000001000010000 : data_out=matrix1[4];
		32'b0000001000010100 : data_out=matrix1[5];
		32'b0000001000011000 : data_out=matrix1[6];
		32'b0000001000011100 : data_out=matrix1[7];
		32'b0000001000100000 : data_out=matrix1[8];

		32'b0000001100000000 : data_out=matrix2[0];
		32'b0000001100000100 : data_out=matrix2[1];
		32'b0000001100001000 : data_out=matrix2[2];
		32'b0000001100001100 : data_out=matrix2[3];
		32'b0000001100010000 : data_out=matrix2[4];
		32'b0000001100010100 : data_out=matrix2[5];
		32'b0000001100011000 : data_out=matrix2[6];
		32'b0000001100011100 : data_out=matrix2[7];
		32'b0000001100100000 : data_out=matrix2[8];
		default : data_out=32'd0;
	endcase
	end
	else if(memwrite==1 && memread==0)
	begin
		case(address)
		32'b0000000100000000 : matrix3[0]=data_in;
		32'b0000000100000100 : matrix3[1]=data_in;
		32'b0000000100001000 : matrix3[2]=data_in;
		32'b0000000100001100 : matrix3[3]=data_in;
		32'b0000000100010000 : matrix3[4]=data_in;
		32'b0000000100010100 : matrix3[5]=data_in;
		32'b0000000100011000 : matrix3[6]=data_in;
		32'b0000000100011100 : matrix3[7]=data_in;
		32'b0000000100100000 : matrix3[8]=data_in;
		default : data_out=data_in;
	endcase
	end
end
assign d11 = matrix3[0];
assign d12 = matrix3[1];
assign d13 = matrix3[2];
assign d21 = matrix3[3];
assign d22 = matrix3[4];
assign d23 = matrix3[5];
assign d31 = matrix3[6];
assign d32 = matrix3[7];
assign d33 = matrix3[8];/*
initial begin
$display("%d",data_in);
//$display("%d %d %d %d %d %d",d11,d12,d13,d21,d22,d23);
end*/
endmodule

ALU_Main.v
module aluMain(controlLines, a, b, out);
    input [3:0] controlLines;
    input [31:0] a, b;
    output reg [31:0] out;

    always @ (*) begin
        case(controlLines)
            4'b0010 : out = a + b;
            4'b0011 : out = a - b;
            4'b0100 : out = a * b;
        endcase
        $display("ALUOUT, b = %d, %d", out, b);
    end
endmodule

ALU_Control_Unit.v
module aluControlUnit(aluOp, f6, out4);
    input [1:0] aluOp;
    input [5:0] f6;
    output reg [3:0] out4;
    always @ (*)//posedge
        begin
            case(aluOp)
                2'b00 : out4=4'b0010;
                2'b10 : case(f6)
                            6'b100000 : out4 = 4'b0010;
                            6'b100010 : out4 = 4'b0011;
                            6'b011000 : out4 = 4'b0100;
                        endcase
            endcase
            // $display("aluControlUnit");//aluOp, out4, f6 = %b,%b,%b", aluOp, out4, f6);
        end
endmodule

Decoder.v
module decoder(address1,address2,dest,regwrite,write_data,out1,out2);
input regwrite;
input [4:0] address1,address2,dest;
input [31:0] write_data;
output [31:0] out1,out2;
wire [31:0] dataOut;
Registers uut1(regwrite,address1,write_data,dataOut);
assign out1=dataOut;
Registers uut2(regwrite,address2,write_data,dataOut);
assign out2=dataOut;
endmodule

Mux1.v
module mux1(data1,data2,sel,out);
input [4:0] data1,data2;
input sel;
output reg [4:0] out;
// assign out=(sel==1'b0)?data1:data2;
// /*
always @ (*)begin//posedge  begin
    case(sel)
        0 : out = data1;
        1 : out = data2;
    endcase
    //$display("mux1\nd1, d2 = %b, %b\nout = %b", data1, data2, out);
end
// */
endmodule

Control_Unit.v
module controlUnit(opcode, ALUout, MemR, MemW, RegW, MemToReg, aluSrc, regDest);
    input [5:0] opcode;

    output reg [1:0] ALUout;
    output reg MemR, MemW, RegW, MemToReg, aluSrc, regDest;

    always @ (*)
        begin
            case(opcode)
                6'b000000 : begin
                                ALUout = 2'b10;
                                RegW = 1;
                                MemR = 0;
                                MemW = 0;
                                MemToReg = 0;
                                aluSrc = 0;
                                regDest = 0;
                            end
                6'b100011 : begin
                                ALUout = 2'b00;
                                RegW = 1;
                                MemR = 1;
                                MemToReg = 1;
                                MemW = 0;
                                aluSrc = 1;
                                regDest = 1;
                            end
                6'b101011 : begin
                                ALUout = 2'b00;
                                RegW = 0;
                                MemR = 0;
                                MemToReg = 1;
                                MemW = 1;
                                aluSrc = 1;
                                regDest = 1;
                            end
            endcase
        end
endmodule

Instruction_memory.v
module instruction_memory(address,data_out);
input [31:0]address;
output [31:0]data_out;
reg [31:0]memory[360:0];
initial begin
		//load word t0 512(s0)
		memory[0]=32'b100011_01000_10000_0000001000000000;
		//load word t1 768(s0)
		memory[4]=32'b100011_01001_10000_0000001100000000;
		//load word t2 516(s0)
		memory[8]=32'b100011_01010_10000_0000001000000100;
		//load word t3 772(s0)
		memory[12]=32'b100011_01011_10000_0000001100000100;
		//load word t4 520(s0)
		memory[16]=32'b100011_01100_10000_0000001000001000;
		//load word t5 776(s0)
		memory[20]=32'b100011_01101_10000_0000001100001000;
		//mul t6 t0 t1
		memory[24]=32'b000000_01110_01000_01001_00000_011000;
		//mul t7 t2 t3
		memory[28]=32'b000000_01111_01010_01011_00000_011000;
		//mul s5 t4 t5
		memory[32]=32'b000000_10101_01100_01101_00000_011000;
		//add t6 t6 t7
		memory[36]=32'b000000_01110_01110_01111_00000_100000;
		//add t6 t6 s5
		memory[40]=32'b000000_01110_01110_10101_00000_100000;
		//
		//store word t6 256(s0)
		memory[44]=33'b101011_01110_10000_0000000100000000;
		//
		//load word t1 780(s0)
		memory[48]=32'b100011_01001_10000_0000001100001100;
		//load word t3 784(s0)
		memory[52]=32'b100011_01011_10000_0000001100010000;
		//load word t5 788(s0)
		memory[56]=32'b100011_01101_10000_0000001100010100;
		//mul t6 t0 t1
		memory[60]=32'b000000_01110_01000_01001_00000_011000;
		//mul t7 t2 t3
		memory[64]=32'b000000_01111_01010_01011_00000_011000;
		//mul s5 t4 t5
		memory[68]=32'b000000_10101_01100_01101_00000_011000;
		//add t6 t6 t7
		memory[72]=32'b000000_01110_01110_01111_00000_100000;
		//add t6 t6 s5
		memory[76]=32'b000000_01110_01110_10101_00000_100000;
		//
		//store word t6 260(s0)
		memory[80]=32'b101011_01110_10000_0000000100000100;
		//
		//load word t1 792(s0)
		memory[84]=32'b100011_01001_10000_0000001100011000;
		//load word t3 796(s0)
		memory[88]=32'b100011_01011_10000_0000001100011100;
		//load word t5 800(s0)
		memory[92]=32'b100011_01101_10000_0000001100100000;
		//mul t6 t0 t1
		memory[96]=32'b000000_01110_01000_01001_00000_011000;
		//mul t7 t2 t3
		memory[100]=32'b000000_01111_01010_01011_00000_011000;
		//mul s5 t4 t5
		memory[104]=32'b000000_10101_01100_01101_00000_011000;
		//add t6 t6 t7
		memory[108]=32'b000000_01110_01110_01111_00000_100000;
		//add t6 t6 s5
		memory[112]=32'b000000_01110_01110_10101_00000_100000;
		//
		//store word t6 264(s0)
		memory[116]=32'b101011_01110_10000_0000000100001000;
		//
		//load word t0 524(s0)
		memory[120]=32'b100011_01000_10000_0000001000001100;
		//load word t2 528(s0)
		memory[124]=32'b100011_01010_10000_0000001000010000;
		//load word t4 532(s0)
		memory[128]=32'b100011_01100_10000_0000001000010100;
		//load word t1 768(s0)
		memory[132]=32'b100011_01001_10000_0000001100000000;
		//load word t3 772(s0)
		memory[136]=32'b100011_01011_10000_0000001100000100;
		//load word t5 776(s0)
		memory[140]=32'b100011_01101_10000_0000001100001000;
		//mul t6 t0 t1
		memory[144]=32'b000000_01110_01000_01001_00000_011000;
		//mul t7 t2 t3
		memory[148]=32'b000000_01111_01010_01011_00000_011000;
		//mul s5 t4 t5
		memory[152]=32'b000000_10101_01100_01101_00000_011000;
		//add t6 t6 t7
		memory[156]=32'b000000_01110_01110_01111_00000_100000;
		//add t6 t6 s5
		memory[160]=32'b000000_01110_01110_10101_00000_100000;
		//
		//store word t6 270(s0)
		memory[164]=32'b101011_01110_10000_0000000100001110;
		//
		//load t1 780(s0)
		memory[168]=32'b100011_01001_10000_0000001100001100;
		//load t3 784(s0)
		memory[172]=32'b100011_01011_10000_0000001100010000;
		//load t5 788(s0)
		memory[176]=32'b100011_01101_10000_0000001100010100;
		//mul t6 t0 t1
		memory[180]=32'b000000_01110_01000_01001_00000_011000;
		//mul t7 t2 t3
		memory[184]=32'b000000_01111_01010_01011_00000_011000;
		//mul s5 t4 t5
		memory[188]=32'b000000_10101_01100_01101_00000_011000;
		//add t6 t6 t7
		memory[192]=32'b000000_01110_01110_01111_00000_100000;
		//add t6 t6 s5
		memory[196]=32'b000000_01110_01110_10101_00000_100000;
		//
		//store word t6 274(s0)
		memory[200]=32'b101011_01110_10000_0000000100010010;
		//
		//load t1 792(s0)
		memory[204]=32'b100011_01001_10000_0000001100011000;
		//load t3 796(s0)
		memory[208]=32'b100011_01011_10000_0000001100011100;
		//load t5 800(s0)
		memory[212]=32'b100011_01101_10000_0000001100100000;
		//mul t6 t0 t1
		memory[216]=32'b000000_01110_01000_01001_00000_011000;
		//mul t7 t2 t3
		memory[220]=32'b000000_01111_01010_01011_00000_011000;
		//mul s5 t4 t5
		memory[224]=32'b000000_10101_01100_01101_00000_011000;
		//add t6 t6 t7
		memory[228]=32'b000000_01110_01110_01111_00000_100000;
		//add t6 t6 s5
		memory[232]=32'b000000_01110_01110_10101_00000_100000;
		//
		//store word t6 280(s0)
		memory[236]=32'b101011_01110_10000_0000000100011000;
		//
		//load t0 536(s0)
		memory[240]=32'b100011_01000_10000_0000001000011000;
		//load t2 540(s0)
		memory[244]=32'b100011_01010_10000_0000001000011100;
		//load t4 544(s0)
		memory[248]=32'b100011_01100_10000_0000001000100000;
		//load t1 768(s0)
		memory[252]=32'b100011_01001_10000_0000001100000000;
		//load t3 772(s0)
		memory[256]=32'b100011_01011_10000_0000001100000100;
		//load t5 776(s0)
		memory[260]=32'b100011_01101_10000_0000001100001000;
		//mul t6 t0 t1
		memory[264]=32'b000000_01110_01000_01001_00000_011000;
		//mul t7 t2 t3
		memory[268]=32'b000000_01111_01010_01011_00000_011000;
		//mul s5 t4 t5
		memory[272]=32'b000000_10101_01100_01101_00000_011000;
		//add t6 t6 t7
		memory[276]=32'b000000_01110_01110_01111_00000_100000;
		//add t6 t6 s5
		memory[280]=32'b000000_01110_01110_10101_00000_100000;
		//
		//store word t6 294(s0)
		memory[284]=32'b101011_01110_10000_0000000100100110;
		//
		//load t1 780(s0)
		memory[288]=32'b100011_01001_10000_0000001100001100;
		//load t3 784(s0)
		memory[292]=32'b100011_01011_10000_0000001100010000;
		//load t5 788(s0)
		memory[296]=32'b100011_01101_10000_0000001100010100;
		//mul t6 t0 t1
		memory[300]=32'b000000_01110_01000_01001_00000_011000;
		//mul t7 t2 t3
		memory[304]=32'b000000_01111_01010_01011_00000_011000;
		//mul s5 t4 t5
		memory[308]=32'b000000_10101_01100_01101_00000_011000;
		//add t6 t6 t7
		memory[312]=32'b000000_01110_01110_01111_00000_100000;
		//add t6 t6 s5
		memory[316]=32'b000000_01110_01110_10101_00000_100000;
		//
		//store t6 298(s0)
		memory[320]=32'b101011_01110_10000_0000000100101010;
		//
		//load t1 792(s0)
		memory[324]=32'b100011_01001_10000_0000001100011000;
		//load t3 796(s0)
		memory[328]=32'b100011_01011_10000_0000001100011100;
		//load t5 800(s0)
		memory[332]=32'b100011_01101_10000_0000001100100000;
		//mul t6 t0 t1
		memory[336]=32'b000000_01110_01000_01001_00000_011000;
		//mul t7 t2 t3
		memory[340]=32'b000000_01111_01010_01011_00000_011000;
		//mul s5 t4 t5
		memory[344]=32'b000000_10101_01100_01101_00000_011000;
		//add t6 t6 t7
		memory[348]=32'b000000_01110_01110_01111_00000_100000;
		//add t6 t6 s5
		memory[352]=32'b000000_01110_01110_10101_00000_100000;
		//
		//store t6 302(s0)
		memory[356]=32'b101011_01110_10000_0000000100101110;
		//
end
assign data_out=memory[address];
initial begin
	$display("%d",data_out);
end
endmodule

main.v
module main(pc,d11,d12,d13,d21,d22,d23,d31,d32,d33);
input [31:0] pc;
wire MemR,MemW,RegW,MemToReg,alusrc,regdest;
wire [1:0] Aluout;
wire [31:0] out1,out2,instruction,b,out_alu;
wire [4:0] dest;
wire [3:0] c_line;
output [31:0] d11,d12,d13,d21,d22,d23,d31,d32,d33;
wire [31:0] a11,a12,a13,a21,a22,a23,a31,a32,a33;
wire [31:0] signExtended,data_out_mem,write_back,dummy;
assign signExtended = {16'b0, instruction[15:0]};
instruction_memory uut1(pc,instruction);
controlUnit uut2(instruction[31:26],Aluout,MemR,MemW,RegW,MemToReg,alusrc,regdest);
mux1 uut3(instruction[25:21],instruction[15:11],regdest,dest);
decoder uut4(instruction[20:16],instruction[25:21],dest,RegW,32'b?,out1,out2);
mux2 uut5(out2,signExtended,alusrc,b);
aluControlUnit uut6(Aluout,instruction[5:0],c_line);
aluMain uut7(c_line,out1,b,out_alu);
MainMemory uut8(MemR,MemW,out_alu,b,data_out_mem,d11,d12,d13,d21,d22,d23,d31,d32,d33);
mux2 uut9(out_alu,data_out_mem,MemToReg,write_back);
Registers uut10(1'b1,dest,write_back,dummy);
initial begin
$display("%d ",instruction);
end
endmodule

Test_Bench.v
module TB_3x3_Multiplication;
    reg [31:0] pc;
    reg clk;

    wire [31:0] d11, d12, d13, d21, d22, d23, d31, d32, d33;

    main uut(
        .pc(pc),
        .d11(d11),
        .d12(d12),
        .d13(d13),
        .d21(d21),
        .d22(d22),
        .d23(d23),
        .d31(d31),
        .d32(d32),
        .d33(d33)
    );

    initial begin
        $dumpfile("mip3x3m.vcd");
        $dumpvars(0, TB_3x3_Multiplication);
        clk = 0; pc = -4; #10;
        repeat(500) #10 clk = ~clk;
        $display("%d \t%d \t%d\n%d \t%d \t%d\n%d \t%d \t%d\n", d11, d12, d13, d21, d22, d23, d31, d32, d33);
    end

    always @ ( posedge clk ) begin
        pc = pc + 4;
        //$display("%d", pc);
    end
endmodule

mip3x3m.vcd
$date
	Fri Nov 23 21:51:37 2018
$end
$version
	Icarus Verilog
$end
$timescale
	1s
$end
$scope module TB_3x3_Multiplication $end
$var wire 32 ! d33 [31:0] $end
$var wire 32 " d32 [31:0] $end
$var wire 32 # d31 [31:0] $end
$var wire 32 $ d23 [31:0] $end
$var wire 32 % d22 [31:0] $end
$var wire 32 & d21 [31:0] $end
$var wire 32 ' d13 [31:0] $end
$var wire 32 ( d12 [31:0] $end
$var wire 32 ) d11 [31:0] $end
$var reg 1 * clk $end
$var reg 32 + pc [31:0] $end
$scope module uut $end
$var wire 32 , pc [31:0] $end
$var wire 32 - write_back [31:0] $end
$var wire 32 . signExtended [31:0] $end
$var wire 1 / regdest $end
$var wire 32 0 out_alu [31:0] $end
$var wire 32 1 out2 [31:0] $end
$var wire 32 2 out1 [31:0] $end
$var wire 32 3 instruction [31:0] $end
$var wire 32 4 dummy [31:0] $end
$var wire 5 5 dest [4:0] $end
$var wire 32 6 data_out_mem [31:0] $end
$var wire 32 7 d33 [31:0] $end
$var wire 32 8 d32 [31:0] $end
$var wire 32 9 d31 [31:0] $end
$var wire 32 : d23 [31:0] $end
$var wire 32 ; d22 [31:0] $end
$var wire 32 < d21 [31:0] $end
$var wire 32 = d13 [31:0] $end
$var wire 32 > d12 [31:0] $end
$var wire 32 ? d11 [31:0] $end
$var wire 4 @ c_line [3:0] $end
$var wire 32 A b [31:0] $end
$var wire 1 B alusrc $end
$var wire 1 C RegW $end
$var wire 1 D MemW $end
$var wire 1 E MemToReg $end
$var wire 1 F MemR $end
$var wire 2 G Aluout [1:0] $end
$scope module uut1 $end
$var wire 32 H address [31:0] $end
$var wire 32 I data_out [31:0] $end
$upscope $end
$scope module uut10 $end
$var wire 1 J regWrite $end
$var wire 5 K regAddress [4:0] $end
$var wire 32 L dataIn [31:0] $end
$var reg 32 M dataOut [31:0] $end
$upscope $end
$scope module uut2 $end
$var wire 6 N opcode [5:0] $end
$var reg 2 O ALUout [1:0] $end
$var reg 1 F MemR $end
$var reg 1 E MemToReg $end
$var reg 1 D MemW $end
$var reg 1 C RegW $end
$var reg 1 B aluSrc $end
$var reg 1 / regDest $end
$upscope $end
$scope module uut3 $end
$var wire 5 P data1 [4:0] $end
$var wire 5 Q data2 [4:0] $end
$var wire 1 / sel $end
$var wire 5 R out [4:0] $end
$upscope $end
$scope module uut4 $end
$var wire 5 S address1 [4:0] $end
$var wire 5 T address2 [4:0] $end
$var wire 32 U dataOut [31:0] $end
$var wire 5 V dest [4:0] $end
$var wire 32 W out1 [31:0] $end
$var wire 32 X out2 [31:0] $end
$var wire 1 C regwrite $end
$var wire 32 Y write_data [31:0] $end
$scope module uut1 $end
$var wire 32 Z dataIn [31:0] $end
$var wire 5 [ regAddress [4:0] $end
$var wire 1 C regWrite $end
$var reg 32 \ dataOut [31:0] $end
$upscope $end
$scope module uut2 $end
$var wire 32 ] dataIn [31:0] $end
$var wire 5 ^ regAddress [4:0] $end
$var wire 1 C regWrite $end
$var reg 32 _ dataOut [31:0] $end
$upscope $end
$upscope $end
$scope module uut5 $end
$var wire 32 ` data1 [31:0] $end
$var wire 32 a data2 [31:0] $end
$var wire 1 B sel $end
$var wire 32 b out [31:0] $end
$upscope $end
$scope module uut6 $end
$var wire 2 c aluOp [1:0] $end
$var wire 6 d f6 [5:0] $end
$var reg 4 e out4 [3:0] $end
$upscope $end
$scope module uut7 $end
$var wire 32 f a [31:0] $end
$var wire 32 g b [31:0] $end
$var wire 4 h controlLines [3:0] $end
$var reg 32 i out [31:0] $end
$upscope $end
$scope module uut8 $end
$var wire 32 j address [31:0] $end
$var wire 32 k d11 [31:0] $end
$var wire 32 l d12 [31:0] $end
$var wire 32 m d13 [31:0] $end
$var wire 32 n d21 [31:0] $end
$var wire 32 o d22 [31:0] $end
$var wire 32 p d23 [31:0] $end
$var wire 32 q d31 [31:0] $end
$var wire 32 r d32 [31:0] $end
$var wire 32 s d33 [31:0] $end
$var wire 32 t data_in [31:0] $end
$var wire 1 F memread $end
$var wire 1 D memwrite $end
$var reg 32 u data_out [31:0] $end
$upscope $end
$scope module uut9 $end
$var wire 32 v data1 [31:0] $end
$var wire 32 w data2 [31:0] $end
$var wire 1 E sel $end
$var wire 32 x out [31:0] $end
$upscope $end
$upscope $end
$upscope $end
$enddefinitions $end
#0
$dumpvars
bx x
bx w
bx v
bx u
bx t
bx s
bx r
bx q
bx p
bx o
bx n
bx m
bx l
bx k
bx j
bx i
bx h
bx g
bx f
bx e
bx d
bx c
bx b
b0xxxxxxxxxxxxxxxx a
bx `
bx _
bx ^
bz ]
bx \
bx [
bz Z
bz Y
bx X
bx W
bx V
bx U
bx T
bx S
bx R
bx Q
bx P
bx O
bx N
bx M
bx L
bx K
1J
bx I
b11111111111111111111111111111100 H
bx G
xF
xE
xD
xC
xB
bx A
bx @
bx ?
bx >
bx =
bx <
bx ;
bx :
bx 9
bx 8
bx 7
bx 6
bx 5
bx 4
bx 3
bx 2
bx 1
bx 0
x/
b0xxxxxxxxxxxxxxxx .
bx -
b11111111111111111111111111111100 ,
b11111111111111111111111111111100 +
0*
bx )
bx (
bx '
bx &
bx %
bx $
bx #
bx "
bx !
$end
#20
b1000000000 A
b1000000000 b
b1000000000 g
b1000000000 t
b0 -
b0 L
b0 x
b0 6
b0 u
b0 w
b10 @
b10 e
b10 h
b0 5
b0 K
b0 R
b0 V
1/
1B
0D
1E
1F
1C
b0 G
b0 O
b0 c
b0 d
b1000 T
b1000 ^
b10000 S
b10000 [
b0 Q
b1000 P
b100011 N
b1000000000 .
b1000000000 a
b10001101000100000000001000000000 3
b10001101000100000000001000000000 I
b0 +
b0 ,
b0 H
1*
#30
0*
#40
b1100000000 A
b1100000000 b
b1100000000 g
b1100000000 t
b1001 T
b1001 ^
b1001 P
b1100000000 .
b1100000000 a
b10001101001100000000001100000000 3
b10001101001100000000001100000000 I
b100 +
b100 ,
b100 H
1*
#50
0*
#60
b1000000100 A
b1000000100 b
b1000000100 g
b1000000100 t
b100 d
b1010 T
b1010 ^
b1010 P
b1000000100 .
b1000000100 a
b10001101010100000000001000000100 3
b10001101010100000000001000000100 I
b1000 +
b1000 ,
b1000 H
1*
#70
0*
#80
b1100000100 A
b1100000100 b
b1100000100 g
b1100000100 t
b1011 T
b1011 ^
b1011 P
b1100000100 .
b1100000100 a
b10001101011100000000001100000100 3
b10001101011100000000001100000100 I
b1100 +
b1100 ,
b1100 H
1*
#90
0*
#100
b1000001000 A
b1000001000 b
b1000001000 g
b1000001000 t
b1000 d
b1100 T
b1100 ^
b1100 P
b1000001000 .
b1000001000 a
b10001101100100000000001000001000 3
b10001101100100000000001000001000 I
b10000 +
b10000 ,
b10000 H
1*
#110
0*
#120
b1100001000 A
b1100001000 b
b1100001000 g
b1100001000 t
b1101 T
b1101 ^
b1101 P
b1100001000 .
b1100001000 a
b10001101101100000000001100001000 3
b10001101101100000000001100001000 I
b10100 +
b10100 ,
b10100 H
1*
#130
0*
#140
bx -
bx L
bx x
b100 @
b100 e
b100 h
b1110 5
b1110 K
b1110 R
b1110 V
0/
0B
0E
0F
b10 G
b10 O
b10 c
bx A
bx b
bx g
bx t
b11000 d
b1110 T
b1110 ^
b1000 S
b1000 [
b1001 Q
b1110 P
b0 N
b100100000011000 .
b100100000011000 a
b1110010000100100000011000 3
b1110010000100100000011000 I
b11000 +
b11000 ,
b11000 H
1*
#150
0*
#160
b1111 5
b1111 K
b1111 R
b1111 V
b1111 T
b1111 ^
b1010 S
b1010 [
b1011 Q
b1111 P
b101100000011000 .
b101100000011000 a
b1111010100101100000011000 3
b1111010100101100000011000 I
b11100 +
b11100 ,
b11100 H
1*
#170
0*
#180
b10101 5
b10101 K
b10101 R
b10101 V
b10101 T
b10101 ^
b1100 S
b1100 [
b1101 Q
b10101 P
b110100000011000 .
b110100000011000 a
b10101011000110100000011000 3
b10101011000110100000011000 I
b100000 +
b100000 ,
b100000 H
1*
#190
0*
#200
b10 @
b10 e
b10 h
b1110 5
b1110 K
b1110 R
b1110 V
b100000 d
b1110 T
b1110 ^
b1110 S
b1110 [
b1111 Q
b1110 P
b111100000100000 .
b111100000100000 a
b1110011100111100000100000 3
b1110011100111100000100000 I
b100100 +
b100100 ,
b100100 H
1*
#210
0*
#220
b10101 Q
b1010100000100000 .
b1010100000100000 a
b1110011101010100000100000 3
b1110011101010100000100000 I
b101000 +
b101000 ,
b101000 H
1*
#230
0*
#240
b100000000 -
b100000000 L
b100000000 x
b0 5
b0 K
b0 R
b0 V
b100000000 A
b100000000 b
b100000000 g
b100000000 t
b100000000 6
b100000000 u
b100000000 w
1/
1B
1D
1E
0C
b0 G
b0 O
b0 c
b0 d
b10000 S
b10000 [
b0 Q
b101011 N
b100000000 .
b100000000 a
b10101101110100000000000100000000 3
b10101101110100000000000100000000 I
b101100 +
b101100 ,
b101100 H
1*
#250
0*
#260
b0 -
b0 L
b0 x
b0 6
b0 u
b0 w
0D
1F
1C
b1100001100 A
b1100001100 b
b1100001100 g
b1100001100 t
b1100 d
b1001 T
b1001 ^
b1001 P
b100011 N
b1100001100 .
b1100001100 a
b10001101001100000000001100001100 3
b10001101001100000000001100001100 I
b110000 +
b110000 ,
b110000 H
1*
#270
0*
#280
b1100010000 A
b1100010000 b
b1100010000 g
b1100010000 t
b10000 d
b1011 T
b1011 ^
b1011 P
b1100010000 .
b1100010000 a
b10001101011100000000001100010000 3
b10001101011100000000001100010000 I
b110100 +
b110100 ,
b110100 H
1*
#290
0*
#300
b1100010100 A
b1100010100 b
b1100010100 g
b1100010100 t
b10100 d
b1101 T
b1101 ^
b1101 P
b1100010100 .
b1100010100 a
b10001101101100000000001100010100 3
b10001101101100000000001100010100 I
b111000 +
b111000 ,
b111000 H
1*
#310
0*
#320
bx -
bx L
bx x
b100 @
b100 e
b100 h
b1110 5
b1110 K
b1110 R
b1110 V
0/
0B
0E
0F
b10 G
b10 O
b10 c
bx A
bx b
bx g
bx t
b11000 d
b1110 T
b1110 ^
b1000 S
b1000 [
b1001 Q
b1110 P
b0 N
b100100000011000 .
b100100000011000 a
b1110010000100100000011000 3
b1110010000100100000011000 I
b111100 +
b111100 ,
b111100 H
1*
#330
0*
#340
b1111 5
b1111 K
b1111 R
b1111 V
b1111 T
b1111 ^
b1010 S
b1010 [
b1011 Q
b1111 P
b101100000011000 .
b101100000011000 a
b1111010100101100000011000 3
b1111010100101100000011000 I
b1000000 +
b1000000 ,
b1000000 H
1*
#350
0*
#360
b10101 5
b10101 K
b10101 R
b10101 V
b10101 T
b10101 ^
b1100 S
b1100 [
b1101 Q
b10101 P
b110100000011000 .
b110100000011000 a
b10101011000110100000011000 3
b10101011000110100000011000 I
b1000100 +
b1000100 ,
b1000100 H
1*
#370
0*
#380
b10 @
b10 e
b10 h
b1110 5
b1110 K
b1110 R
b1110 V
b100000 d
b1110 T
b1110 ^
b1110 S
b1110 [
b1111 Q
b1110 P
b111100000100000 .
b111100000100000 a
b1110011100111100000100000 3
b1110011100111100000100000 I
b1001000 +
b1001000 ,
b1001000 H
1*
#390
0*
#400
b10101 Q
b1010100000100000 .
b1010100000100000 a
b1110011101010100000100000 3
b1110011101010100000100000 I
b1001100 +
b1001100 ,
b1001100 H
1*
#410
0*
#420
b100000100 -
b100000100 L
b100000100 x
b0 5
b0 K
b0 R
b0 V
b100000100 A
b100000100 b
b100000100 g
b100000100 t
b100000100 6
b100000100 u
b100000100 w
1/
1B
1D
1E
0C
b0 G
b0 O
b0 c
b100 d
b10000 S
b10000 [
b0 Q
b101011 N
b100000100 .
b100000100 a
b10101101110100000000000100000100 3
b10101101110100000000000100000100 I
b1010000 +
b1010000 ,
b1010000 H
1*
#430
0*
#440
b0 -
b0 L
b0 x
b0 6
b0 u
b0 w
0D
1F
1C
b1100011000 A
b1100011000 b
b1100011000 g
b1100011000 t
b11000 d
b1001 T
b1001 ^
b1001 P
b100011 N
b1100011000 .
b1100011000 a
b10001101001100000000001100011000 3
b10001101001100000000001100011000 I
b1010100 +
b1010100 ,
b1010100 H
1*
#450
0*
#460
b1100011100 A
b1100011100 b
b1100011100 g
b1100011100 t
b11100 d
b1011 T
b1011 ^
b1011 P
b1100011100 .
b1100011100 a
b10001101011100000000001100011100 3
b10001101011100000000001100011100 I
b1011000 +
b1011000 ,
b1011000 H
1*
#470
0*
#480
b1100100000 A
b1100100000 b
b1100100000 g
b1100100000 t
b100000 d
b1101 T
b1101 ^
b1101 P
b1100100000 .
b1100100000 a
b10001101101100000000001100100000 3
b10001101101100000000001100100000 I
b1011100 +
b1011100 ,
b1011100 H
1*
#490
0*
#500
bx -
bx L
bx x
b100 @
b100 e
b100 h
b1110 5
b1110 K
b1110 R
b1110 V
0/
0B
0E
0F
b10 G
b10 O
b10 c
bx A
bx b
bx g
bx t
b11000 d
b1110 T
b1110 ^
b1000 S
b1000 [
b1001 Q
b1110 P
b0 N
b100100000011000 .
b100100000011000 a
b1110010000100100000011000 3
b1110010000100100000011000 I
b1100000 +
b1100000 ,
b1100000 H
1*
#510
0*
#520
b1111 5
b1111 K
b1111 R
b1111 V
b1111 T
b1111 ^
b1010 S
b1010 [
b1011 Q
b1111 P
b101100000011000 .
b101100000011000 a
b1111010100101100000011000 3
b1111010100101100000011000 I
b1100100 +
b1100100 ,
b1100100 H
1*
#530
0*
#540
b10101 5
b10101 K
b10101 R
b10101 V
b10101 T
b10101 ^
b1100 S
b1100 [
b1101 Q
b10101 P
b110100000011000 .
b110100000011000 a
b10101011000110100000011000 3
b10101011000110100000011000 I
b1101000 +
b1101000 ,
b1101000 H
1*
#550
0*
#560
b10 @
b10 e
b10 h
b1110 5
b1110 K
b1110 R
b1110 V
b100000 d
b1110 T
b1110 ^
b1110 S
b1110 [
b1111 Q
b1110 P
b111100000100000 .
b111100000100000 a
b1110011100111100000100000 3
b1110011100111100000100000 I
b1101100 +
b1101100 ,
b1101100 H
1*
#570
0*
